Workbook

Sheet ปะหน้า
A1: Y.K. Logistics CO., LTD. บริษัท วาย.เค. ลอจิสติค จำกัด (สำนักงานใหญ่) 70 หมู่ 5 ตำบล เชียงรากน้อย อำเภอบางปะอิน จังหวัดพระนครศรีอยุธยา 13180 เลขประจำตัวผู้เสียภาษี 0125548009248
A6: ใบปะหน้าวางบิลค่าขนส่ง
A8: ชื่อลูกค้า/Customer | B8: =ค่าขนส่ง!C11 -> CJ Logistics (Thailand) Co.,Ltd.
I9: วันที่ Date | J9: =ค่าขนส่ง!K8 -> 46183
I10: Rev.
A11: ที่อยู่ / Adress | B11: =ค่าขนส่ง!C12 -> 598 Q House Pleonchit Building, 16th Fl., Pleonchit rd., Lumphinee, Pathumwan, Bangkok 10330
B12: =ค่าขนส่ง!C13 -> TAX ID : 0105547034923 | I12: เงื่อนไขการชำระเงิน | J12: วันที่ครบกำหนด
A14: ลำดับที่ | C14: รายละเอียด | H14: จำนวน | I14: ราคาต่อหน่วย | J14: จำนวนเงิน
A15: Item | C15: Description | H15: Quantity | I15: Unit / Price | J15: Amount
A16: 1 | B16: =ค่าขนส่ง!$G$8&" "&ค่าขนส่ง!$G16&" "&"ค่าขนส่ง" -> CJIV2606-001 HAIER APPLIANCES ค่าขนส่ง | H16: 1 | I16: =ค่าขนส่ง!J26 -> 49800 | J16: =I16 -> 49800
A37: บาท (Baht) | C37: =BAHTTEXT(J39) -> สี่หมื่นเก้าพันแปดร้อยบาทถ้วน | H37: รวมเงิน (Subtotal) | J37: =SUM(J14:J36) -> 49800
H38: ภาษีมูลค่าเพิ่ม (Value Added Tax) 7% | J38: 0
H39: จำนวนเงินทั้งสิ้น (Grand Total) | J39: =SUM(J37:J38) -> 49800
A43: ผู้วางบิล | F43: ผู้รับใบวางบิล | I43: วันนัดรับเช็ค
A47: ใบแจ้งหนี้ทุกฉบับจะต้องชำระเงินภายในเวลาที่ตกลงกันไว้ และ/หรือ ชำระเงินภายในกำหนดข้างต้น มิฉะนั้นทางบริษัทฯจะคิดอัตราดอกเบี้ย ตามที่กฎหมายระบุไว้สูงสุด เมื่อชำระเงินแล้วโปรดเรียกใบเสร็จรับเงิน จากทางบริษัทฯทุกครั้ง

Sheet ค่าขนส่ง
A1: Y.K. Logistics Co.,ltd
A2: บริษัท วาย.เค. ลอจิสติค จำกัด (สำนักงานใหญ่)
A3: 70 หมู่ 5 ตำบลเชียงรากน้อย อำเภอบางปะอิน จังหวัดพระนครศรีอยุธยา 13180
A4: เลขประจำตัวผู้เสียภาษี 0125548009248
A5: ใบแจ้งหนี้ / INVOICE
A8: ใบแจ้งหนี้เลขที่ | G8: CJIV2606-001 | J8: วันที่ | K8: 46183
J9: DATE
A11: CUSTOMER : | C11: CJ Logistics (Thailand) Co.,Ltd.
A12: ADDRESS : | C12: 598 Q House Pleonchit Building, 16th Fl., Pleonchit rd., Lumphinee, Pathumwan, Bangkok 10330
C13: TAX ID : 0105547034923 | K13: เรทน้ำมัน = 41.72
A14: ลำดับ | B14: รายการบรรทุก | D14: CONT | E14: SIZE | F14: ทะเบียนรถ | G14: CUST. | H14: JOB | I14: วันที่บรรทุก | J14: จำนวนเงิน | K14: หมายเหตุ
A15: ITEM | B15: TRUCK LIST | F15: TRUCK NO. | I15: DATE | J15: AMOUNT | K15: REMAKR
A16: 1 | B16: LCB -VR304 | D16: OOCU8053610 | E16: 40 | F16: 71-9627 | G16: HAIER APPLIANCES | H16: COAU7269153180 | I16: 46178 | J16: 8300 | K16: ค่าขนส่ง
A17: 2 | B17: LCB -VR304 | D17: OOLU9157596 | E17: 40 | F17: 72-1217 | G17: HAIER APPLIANCES | H17: COAU7269149760 | I17: 46178 | J17: 8300 | K17: ค่าขนส่ง
A18: 3 | B18: LCB -VR304 | D18: CSNU7866168 | E18: 40 | F18: 72-1218 | G18: HAIER APPLIANCES | H18: COAU7269153180 | I18: 46178 | J18: 8300 | K18: ค่าขนส่ง
A19: 4 | B19: LCB -TRI-WALL | D19: TRHU6140014 | E19: 40 | F19: 71-9627 | G19: HAIER APPLIANCES | H19: CULVNAS2618583 | I19: 46179 | J19: 8300 | K19: ค่าขนส่ง
A20: 5 | B20: LCB -VR304 | D20: TEMU3133511 | E20: 20 | F20: 71-6802 | G20: HAIER APPLIANCES | H20: COAU7269159720W | I20: 46179 | J20: 8300 | K20: ค่าขนส่ง
A21: 6 | B21: LCB -TRI-WALL | D21: TIIU6896809 | E21: 40 | F21: 71-8681 | G21: HAIER APPLIANCES | H21: CULVNAS2618583 | I21: 46179 | J21: 8300 | K21: ค่าขนส่ง
A26: =BAHTTEXT(J26) -> สี่หมื่นเก้าพันแปดร้อยบาทถ้วน | J26: =SUM(J16:J25) -> 49800
A30: ผู้วางบิล.……………………….………
A31: วันที่ | B31: =K8 -> 46183
A34: หมายเหตุ : ใบแจ้งนี้ทุกฉบับจะต้องชำระเงินภายในเวลาที่ตกลงกันไว้และ/หรือ ชำระเงินภายในกำหนดข้างต้น มิฉะนั้นทางบริษัทฯจะคิดอัตราดอกเบี้ย
A35: ตามที่กฎหมายระบุไว้สูงสุด เมื่อชำระเงินแล้วโปรดเรียกใบเสร็จรับเงิน จากบริษัทฯทุกครั้ง

Sheet ปะหน้า (2)
A1: Y.K. Logistics CO., LTD. บริษัท วาย.เค. ลอจิสติค จำกัด (สำนักงานใหญ่) 70 หมู่ 5 ตำบล เชียงรากน้อย อำเภอบางปะอิน จังหวัดพระนครศรีอยุธยา 13180 เลขประจำตัวผู้เสียภาษี 0125548009248
A6: ใบปะหน้าวางบิลค่าขนส่ง
A8: ชื่อลูกค้า/Customer | B8: =ค่าขนส่ง!C11 -> CJ Logistics (Thailand) Co.,Ltd.
I9: วันที่ Date | J9: =ค่าขนส่ง!K8 -> 46183
I10: Rev.
A11: ที่อยู่ / Adress | B11: =ค่าขนส่ง!C12 -> 598 Q House Pleonchit Building, 16th Fl., Pleonchit rd., Lumphinee, Pathumwan, Bangkok 10330
B12: =ค่าขนส่ง!C13 -> TAX ID : 0105547034923 | I12: เงื่อนไขการชำระเงิน | J12: วันที่ครบกำหนด
A14: ลำดับที่ | C14: รายละเอียด | H14: จำนวน | I14: ราคาต่อหน่วย | J14: จำนวนเงิน
A15: Item | C15: Description | H15: Quantity | I15: Unit / Price | J15: Amount
A16: 1 | B16: =ค่าทดรองจ่าย!$G$8&" "&ค่าทดรองจ่าย!$G16&" "&"ค่าใช้จ่าย" -> CJIV2606-001AD HAIER APPLIANCES ค่าใช้จ่าย | H16: 1 | I16: =ค่าทดรองจ่าย!O26 -> 6685.05 | J16: =I16 -> 6685.05
A36: บาท (Baht) | C36: =BAHTTEXT(J38) -> หกพันหกร้อยแปดสิบห้าบาทห้าสตางค์ | H36: รวมเงิน (Subtotal) | J36: =SUM(J14:J35) -> 6685.05
H37: ภาษีมูลค่าเพิ่ม (Value Added Tax) 7% | J37: 0
H38: จำนวนเงินทั้งสิ้น (Grand Total) | J38: =SUM(J36:J37) -> 6685.05
A42: ผู้วางบิล | F42: ผู้รับใบวางบิล | I42: วันนัดรับเช็ค
A46: ใบแจ้งหนี้ทุกฉบับจะต้องชำระเงินภายในเวลาที่ตกลงกันไว้ และ/หรือ ชำระเงินภายในกำหนดข้างต้น มิฉะนั้นทางบริษัทฯจะคิดอัตราดอกเบี้ย ตามที่กฎหมายระบุไว้สูงสุด เมื่อชำระเงินแล้วโปรดเรียกใบเสร็จรับเงิน จากทางบริษัทฯทุกครั้ง

Sheet ค่าทดรองจ่าย
A1: Y.K. Logistics Co.,ltd
A2: บริษัท วาย.เค. ลอจิสติค จำกัด (สำนักงานใหญ่)
A3: 70 หมู่ 5 ตำบลเชียงรากน้อย อำเภอบางปะอิน จังหวัดพระนครศรีอยุธยา 13180
A4: เลขประจำตัวผู้เสียภาษี 0125548009248
A5: ใบแจ้งหนี้ทดรองจ่าย / Advance Billing
A8: ใบแจ้งยอดทดรองเลขที่ | G8: =""&ค่าขนส่ง!G8&"AD" -> CJIV2606-001AD | M8: วันที่ | O8: =ค่าขนส่ง!K8 -> 46183
M9: DATE
A11: CUSTOMER : | C11: =ค่าขนส่ง!C11 -> CJ Logistics (Thailand) Co.,Ltd.
A12: ADDRESS : | C12: =ค่าขนส่ง!C12 -> 598 Q House Pleonchit Building, 16th Fl., Pleonchit rd., Lumphinee, Pathumwan, Bangkok 10330
C13: =ค่าขนส่ง!C13 -> TAX ID : 0105547034923
A14: ลำดับ | B14: รายการบรรทุก | D14: CONT | E14: SIZE | F14: ทะเบียนรถ | G14: CUST. | H14: JOB | I14: วันที่บรรทุก | J14: ค่ายก | K14: ค่าผ่านลาน | L14: ค่าล้าง/ซ่อม | M14: ค่าเข้าท่า | N14: หัก ณ ที่จ่าย | O14: จำนวนเงิน
A15: ITEM | B15: TRUCK LIST | F15: TRUCK NO. | I15: DATE | J15: Lift on | K15: Gate charge | L15: Cleaning cost | M15: Port toll fee | N15: Withholding tax | O15: AMOUNT
A16: 1 | B16: LCB -VR304 | D16: OOCU8053610 | E16: 40 | F16: 71-9627 | G16: HAIER APPLIANCES | H16: COAU7269153180 | I16: 46178 | M16: 100 | O16: =SUM(J16:M16)-N16 -> 100
A17: 2 | B17: LCB -VR304 | D17: OOLU9157596 | E17: 40 | F17: 72-1217 | G17: HAIER APPLIANCES | H17: COAU7269149760 | I17: 46178 | M17: 200 | O17: =SUM(J17:M17)-N17 -> 200
A18: 3 | B18: LCB -VR304 | D18: CSNU7866168 | E18: 40 | F18: 72-1218 | G18: HAIER APPLIANCES | H18: COAU7269153180 | I18: 46178 | M18: 100 | O18: =SUM(J18:M18)-N18 -> 100
A19: 4 | B19: LCB -TRI-WALL | D19: TRHU6140014 | E19: 40 | F19: 71-9627 | G19: HAIER APPLIANCES | H19: CULVNAS2618583 | I19: 46179 | J19: 1284 | K19: 250 | M19: 100 | N19: 36 | O19: =SUM(J19:M19)-N19 -> 1598
A20: 5 | B20: LCB -VR304 | D20: TEMU3133511 | E20: 20 | F20: 71-6802 | G20: HAIER APPLIANCES | H20: COAU7269159720W | I20: 46179 | J20: 695.5 | K20: 270 | L20: 2123.55 | O20: =SUM(J20:M20)-N20 -> 3089.05
A21: 6 | B21: LCB -TRI-WALL | D21: TIIU6896809 | E21: 40 | F21: 71-8681 | G21: HAIER APPLIANCES | H21: CULVNAS2618583 | I21: 46179 | J21: 1284 | K21: 250 | M21: 100 | N21: 36 | O21: =SUM(J21:M21)-N21 -> 1598
A26: =BAHTTEXT(M26) -> หกร้อยบาทถ้วน | J26: =SUM(J16:J25) -> 3263.5 | K26: =SUM(K16:K25) -> 770 | L26: =SUM(L16:L25) -> 2123.55 | M26: =SUM(M16:M25) -> 600 | N26: =SUM(N16:N25) -> 72 | O26: =SUM(O16:O25) -> 6685.05
A30: ผู้วางบิล.……………………….………
A31: วันที่ | B31: =O8 -> 46183
A34: หมายเหตุ : ใบแจ้งนี้ทุกฉบับจะต้องชำระเงินภายในเวลาที่ตกลงกันไว้และ/หรือ ชำระเงินภายในกำหนดข้างต้น มิฉะนั้นทางบริษัทฯจะคิดอัตราดอกเบี้ย
A35: ตามที่กฎหมายระบุไว้สูงสุด เมื่อชำระเงินแล้วโปรดเรียกใบเสร็จรับเงิน จากบริษัทฯทุกครั้ง
